sinophone/__init__.py
sinophone/sinophone.py
sinophone_zh-0.0.3.dist-info/licenses/LICENSE
sinophone_zh-0.0.3.dist-info/METADATA
sinophone_zh-0.0.3.dist-info/WHEEL
sinophone_zh-0.0.3.dist-info/top_level.txt
sinophone_zh-0.0.3.dist-info/RECORD
