Metadata-Version: 2.4
Name: sinophone-zh
Version: 0.0.3
Summary: 中华音码（SinoPhone）- 中文拼音语音模糊哈希编码算法
Home-page: https://github.com/Johnless31/SinoPhone
Author: johnless
Author-email: johnless <346656208@qq.com>
Maintainer-email: johnless <346656208@qq.com>
License: MIT
Project-URL: Homepage, https://github.com/Johnless31/SinoPhone
Project-URL: Repository, https://github.com/Johnless31/SinoPhone
Project-URL: Issues, https://github.com/Johnless31/SinoPhone/issues
Project-URL: Documentation, https://github.com/Johnless31/SinoPhone#readme
Keywords: chinese,pinyin,phonetic,hash,encoding,sinophone,中文,拼音,语音编码
Classifier: Development Status :: 4 - Beta
Classifier: Intended Audience :: Developers
Classifier: Topic :: Software Development :: Libraries :: Python Modules
Classifier: Topic :: Text Processing :: Linguistic
Classifier: License :: OSI Approved :: MIT License
Classifier: Programming Language :: Python :: 3
Classifier: Programming Language :: Python :: 3.6
Classifier: Programming Language :: Python :: 3.7
Classifier: Programming Language :: Python :: 3.8
Classifier: Programming Language :: Python :: 3.9
Classifier: Programming Language :: Python :: 3.10
Classifier: Programming Language :: Python :: 3.11
Classifier: Natural Language :: Chinese (Simplified)
Classifier: Natural Language :: Chinese (Traditional)
Requires-Python: >=3.6
License-File: LICENSE
Requires-Dist: pypinyin>=0.44.0
Provides-Extra: dev
Requires-Dist: pytest>=6.0; extra == "dev"
Requires-Dist: pytest-cov; extra == "dev"
Requires-Dist: flake8; extra == "dev"
Requires-Dist: black; extra == "dev"
Dynamic: author
Dynamic: home-page
Dynamic: license-file
Dynamic: requires-python
